Verilog Files {Required}/Control (Coded - Tested)/Control.v

module Control
(
	input clock,
	input[31:21] instruction,
	
	output NotZeroBranch,
	output Reg2Loc,
	output Uncondbranch,
	output ZeroBranch,
	output MemRead,
	output MemtoReg,
	output[1:0] ALUOp,
	output MemWrite,
	output ALUSrc,
	output RegWrite
);
	
	reg NotZeroBranch;
	reg Reg2Loc;
	reg Uncondbranch;
	reg ZeroBranch;
	reg MemRead;
	reg MemtoReg;
	reg[1:0] ALUOp;
	reg MemWrite;
	reg ALUSrc;
	reg RegWrite;
	
	
	initial begin  //On being initialized, all output values or set to non-boolean value of 'z'
	
		 NotZeroBranch = 1'bz;
		 Reg2Loc = 1'bz;
		 Uncondbranch = 1'bz;
		 ZeroBranch = 1'bz;
		 MemRead = 1'bz;
		 MemtoReg = 1'bz;
		 ALUOp = 1'bz;
		 MemWrite = 1'bz;
		 ALUSrc = 1'bz;
		 RegWrite = 1'bz;
		
	end
	
	always @(posedge clock) 
	begin
		if(instruction[31:26] == 6'b000101) // B Inst
			begin
				NotZeroBranch = 0;
				Reg2Loc = 0;
				Uncondbranch = 1;
				ZeroBranch = 0;
				MemRead = 0;
				MemtoReg = 0;
				ALUOp = 2'b11;
				MemWrite = 0;
				ALUSrc = 0;
				RegWrite = 0;
			end
		else
			begin
				if(instruction[31:22] == 10'b1001000100) // ADDI Inst
					begin
						NotZeroBranch = 0;
						Reg2Loc = 0;
						Uncondbranch = 0;
						ZeroBranch = 0;
						MemRead = 0;
						MemtoReg = 0;
						ALUOp = 2'b00;
						MemWrite = 0;
						ALUSrc = 1;
						RegWrite = 1;
					end
				else
					begin 
						if(!instruction[27])
							begin
								case(instruction[31:24]) // CB-type inst.s
									8'b10110100: // CBZ Inst
										begin
											NotZeroBranch = 0;
											Reg2Loc = 1;
											Uncondbranch = 0;
											ZeroBranch = 1;
											MemRead = 0;
											MemtoReg = 0;
											ALUOp = 2'b01;
											MemWrite = 0;
											ALUSrc = 0;
											RegWrite = 0;
										end
									8'b10110101: // CBNZ Inst
										begin
											NotZeroBranch = 1;
											Reg2Loc = 1;
											Uncondbranch = 0;
											ZeroBranch = 0;
											MemRead = 0;
											MemtoReg = 0;
											ALUOp = 2'b11;
											MemWrite = 0;
											ALUSrc = 0;
											RegWrite = 0;
										end
								endcase
							end
						else
							begin
								case(instruction) // Rest of R-type, and D-type inst.s
									11'b00111000010: // LDUR Inst
										begin 
											NotZeroBranch = 0;
											Reg2Loc = 0;
											Uncondbranch = 0;
											ZeroBranch = 0;
											MemRead = 1;
											MemtoReg = 1;
											ALUOp = 2'b00;
											MemWrite = 0;
											ALUSrc = 1;
											RegWrite = 1;
										end
									11'b00111000000: // STUR Inst
										begin 
											NotZeroBranch = 0;
											Reg2Loc = 1;
											Uncondbranch = 0;
											ZeroBranch = 0;
											MemRead = 0;
											MemtoReg = 0;
											ALUOp = 2'b00;
											MemWrite = 1;
											ALUSrc = 1;
											RegWrite = 0;
										end
									11'b10001011000: // ADD Inst
										begin
											NotZeroBranch = 0;
											Reg2Loc = 0;
											Uncondbranch = 0;
											ZeroBranch = 0;
											MemRead = 0;
											MemtoReg = 0;
											ALUOp = 2'b00;
											MemWrite = 0;
											ALUSrc = 0;
											RegWrite = 1;
										end
									11'b11001011000: // SUB Inst
										begin
											NotZeroBranch = 0;
											Reg2Loc = 0;
											Uncondbranch = 0;
											ZeroBranch = 0;
											MemRead = 0;
											MemtoReg = 0;
											ALUOp = 2'b10;
											MemWrite = 0;
											ALUSrc = 0;
											RegWrite = 1;
										end
									11'b10001010000: // AND Inst
										begin
											NotZeroBranch = 0;
											Reg2Loc = 0;
											Uncondbranch = 0;
											ZeroBranch = 0;
											MemRead = 0;
											MemtoReg = 0;
											ALUOp = 2'b10;
											MemWrite = 0;
											ALUSrc = 0;
											RegWrite = 1;
										end
									11'b10101010000: // ORR Inst
										begin
											NotZeroBranch = 0;
											Reg2Loc = 0;
											Uncondbranch = 0;
											ZeroBranch = 0;
											MemRead = 0;
											MemtoReg = 0;
											ALUOp = 2'b10;
											MemWrite = 0;
											ALUSrc = 0;
											RegWrite = 1;
										end
								endcase
							end
					end
			end
	end	
endmodule	
		
		
		
		
		
		
		
		
		
		
		
		
		
		
		
		
		
		
		
		
							/*
								NotZeroBranch = 0;
								Reg2Loc = 0;
								Uncondbranch = 0;
								ZeroBranch = 0;
								MemRead = 0;
								MemtoReg = 0;
								ALUOp = 2'b00;
								MemWrite = 0;
								ALUSrc = 0;
								RegWrite = 0;	
							*/

Verilog Files {Required}/Control (Coded - Tested)/Control_tb.v
/*
	Unsigned
*/

`include "Control.v"

module Control_tb;

  reg clock;
  reg[31:21] instruction;

  wire NotZeroBranch;
  wire Reg2Loc;
  wire Uncondbranch;
  wire ZeroBranch;
  wire MemRead;
  wire MemtoReg;
  wire[1:0] ALUOp;
  wire MemWrite;
  wire ALUSrc;
  wire RegWrite;
  
  Control Control_1
  (
	clock,
	instruction,
	NotZeroBranch,
	Reg2Loc,
	Uncondbranch,
	ZeroBranch,
	MemRead,
	MemtoReg,
	ALUOp,
	MemWrite,
	ALUSrc,
	RegWrite
  ); 

  initial
   begin
    $dumpfile("Control.vcd");
	$dumpvars;
	clock <= 1; instruction <= 11'b00111000010; //LDUR
	#5
	clock <= 0;
	#5
	clock <= 1; instruction <= 11'b00111000000; //STUR
	#5
	clock <= 0;
	#5
	clock <= 1; instruction <= 11'b10001011000; //ADD
	#5
	clock <= 0;
	#5
	clock <= 1; instruction <= 11'b10010001000; //ADDI 
	#5
	clock <= 0;
	#5
	clock <= 1; instruction <= 11'b11001011000; //SUB
	#5
	clock <= 0;
	#5
	clock <= 1; instruction <= 11'b10001010000; //AND
	#5
	clock <= 0;
	#5
	clock <= 1; instruction <= 11'b10101010000; //ORR
	#5
	clock <= 0;
	#5
	clock <= 1; instruction <= 11'b10110100000; //CBZ
	#5
	clock <= 0;
	#5
	clock <= 1; instruction <= 11'b10110101000; //CBNZ
	#5
	clock <= 0;
	#5
	clock <= 1; instruction <= 11'b00010100000; //B
	#5
	clock <= 0;
   end
  initial
   begin
      $monitor("time=%4d : inst = %b : NZB = %b : R2L = %b : UncondB = %b : ZBranch = %b : MRead = %b : MtR = %b : ALUOp = %b : ALUsrc = %b : RegWrite = %b", $time, instruction, NotZeroBranch, Reg2Loc, Uncondbranch, ZeroBranch, MemRead, MemtoReg, ALUOp, MemWrite, ALUSrc, RegWrite);
   end
endmodule

Verilog Files {Required}/_Runs/Control.v/Control.vcd
$date
	Sun Mar 25 18:34:37 2018
$end
$version
	Icarus Verilog
$end
$timescale
	1s
$end
$scope module Control_tb $end
$var wire 1 ! ZeroBranch $end
$var wire 1 " Uncondbranch $end
$var wire 1 # RegWrite $end
$var wire 1 $ Reg2Loc $end
$var wire 1 % NotZeroBranch $end
$var wire 1 & MemtoReg $end
$var wire 1 ' MemWrite $end
$var wire 1 ( MemRead $end
$var wire 1 ) ALUSrc $end
$var wire 2 * ALUOp [1:0] $end
$var reg 1 + clock $end
$var reg 11 , instruction [31:21] $end
$scope module Control_1 $end
$var wire 1 + clock $end
$var wire 11 - instruction [31:21] $end
$var reg 2 . ALUOp [1:0] $end
$var reg 1 ) ALUSrc $end
$var reg 1 ( MemRead $end
$var reg 1 ' MemWrite $end
$var reg 1 & MemtoReg $end
$var reg 1 % NotZeroBranch $end
$var reg 1 $ Reg2Loc $end
$var reg 1 # RegWrite $end
$var reg 1 " Uncondbranch $end
$var reg 1 ! ZeroBranch $end
$upscope $end
$upscope $end
$enddefinitions $end
#0
$dumpvars
b0 .
b111000010 -
b111000010 ,
1+
b0 *
1)
1(
0'
1&
0%
0$
1#
0"
0!
$end
#5
0+
#10
0#
1'
0&
0(
1$
b111000000 ,
b111000000 -
1+
#15
0+
#20
1#
0)
0'
0$
b10001011000 ,
b10001011000 -
1+
#25
0+
#30
1)
b10010001000 ,
b10010001000 -
1+
#35
0+
#40
0)
b10 *
b10 .
b11001011000 ,
b11001011000 -
1+
#45
0+
#50
b10001010000 ,
b10001010000 -
1+
#55
0+
#60
b10101010000 ,
b10101010000 -
1+
#65
0+
#70
0#
b1 *
b1 .
1!
1$
b10110100000 ,
b10110100000 -
1+
#75
0+
#80
0!
1%
b10110101000 ,
b10110101000 -
1+
#85
0+
#90
b11 *
b11 .
1"
0$
0%
b10100000 ,
b10100000 -
1+
#95
0+
#100
b1 *
b1 .
1!
0"
1$
b1010100000 ,
b1010100000 -
1+
